kichin_fastapi/__init__.py
kichin_fastapi/models/__init__.py
kichin_fastapi/models/base.py
kichin_fastapi/models/dataset.py
kichin_fastapi-0.3.1.dist-info/METADATA
kichin_fastapi-0.3.1.dist-info/WHEEL
kichin_fastapi-0.3.1.dist-info/RECORD
