Metadata-Version: 2.4
Name: kichin-fastapi
Version: 0.3.1
Summary: FastAPI application for Kichin
Requires-Python: >=3.12
Requires-Dist: pydantic>=2.12.5
Requires-Dist: pyyaml>=6.0
